airflow_installer/__init__.py
airflow_installer/__main__.py
airflow_installer-0.1.0.dist-info/LICENSE
airflow_installer-0.1.0.dist-info/METADATA
airflow_installer-0.1.0.dist-info/WHEEL
airflow_installer-0.1.0.dist-info/entry_points.txt
airflow_installer-0.1.0.dist-info/RECORD
